govuk_flask_admin/__init__.py
govuk_flask_admin/widgets.py
govuk_flask_admin/templates/select-with-search.html
govuk_flask_admin/templates/admin/actions.html
govuk_flask_admin/templates/admin/base.html
govuk_flask_admin/templates/admin/index.html
govuk_flask_admin/templates/admin/layout.html
govuk_flask_admin/templates/admin/lib.html
govuk_flask_admin/templates/admin/master.html
govuk_flask_admin/templates/admin/static.html
govuk_flask_admin/templates/admin/model/create.html
govuk_flask_admin/templates/admin/model/details.html
govuk_flask_admin/templates/admin/model/edit.html
govuk_flask_admin/templates/admin/model/inline_field_list.html
govuk_flask_admin/templates/admin/model/inline_form.html
govuk_flask_admin/templates/admin/model/inline_list_base.html
govuk_flask_admin/templates/admin/model/layout.html
govuk_flask_admin/templates/admin/model/list.html
govuk_flask_admin/templates/admin/model/row_actions.html
govuk_flask_admin/templates/admin/rediscli/console.html
govuk_flask_admin/templates/admin/rediscli/response.html
govuk_flask_admin/static/dist/manifest.json
govuk_flask_admin/static/dist/assets/main-7IBuVhAt.js
govuk_flask_admin/static/dist/assets/main-BF9k5ahw.css
govuk_flask_admin/static/dist/assets/manifest.json
govuk_flask_admin/static/dist/assets/fonts/bold-affa96571d-v2.woff
govuk_flask_admin/static/dist/assets/fonts/bold-b542beb274-v2.woff2
govuk_flask_admin/static/dist/assets/fonts/light-94a07e06a1-v2.woff2
govuk_flask_admin/static/dist/assets/fonts/light-f591b13f7d-v2.woff
govuk_flask_admin/static/dist/assets/images/favicon.ico
govuk_flask_admin/static/dist/assets/images/favicon.svg
govuk_flask_admin/static/dist/assets/images/govuk-crest.svg
govuk_flask_admin/static/dist/assets/images/govuk-icon-180.png
govuk_flask_admin/static/dist/assets/images/govuk-icon-192.png
govuk_flask_admin/static/dist/assets/images/govuk-icon-512.png
govuk_flask_admin/static/dist/assets/images/govuk-icon-mask.svg
govuk_flask_admin-0.2.4.dist-info/METADATA
govuk_flask_admin-0.2.4.dist-info/WHEEL
govuk_flask_admin-0.2.4.dist-info/RECORD
