Metadata-Version: 2.4
Name: govuk-flask-admin
Version: 0.2.4
Summary: Add your description here
Requires-Python: >=3.10
Requires-Dist: email-validator>=2.0.0
Requires-Dist: flask-admin>=2.0.0a0
Requires-Dist: flask>=3
Requires-Dist: govuk-frontend-jinja==3.8.0
Requires-Dist: govuk-frontend-wtf==3.2.0
